sayancpe586fa25/__init__.py
sayancpe586fa25/_core.pyi
sayancpe586fa25/py.typed
sayancpe586fa25/differential/__init__.py
sayancpe586fa25/differential/discrete.py
sayancpe586fa25/distributions/__init__.py
sayancpe586fa25/distributions/cvdistributions.py
sayancpe586fa25/matrix/__init__.py
sayancpe586fa25/matrix/elementary.py
sayancpe586fa25/model/__init__.py
sayancpe586fa25/model/regression.py
sayancpe586fa25-4.5.0.dist-info/METADATA
sayancpe586fa25-4.5.0.dist-info/WHEEL
sayancpe586fa25-4.5.0.dist-info/top_level.txt
sayancpe586fa25-4.5.0.dist-info/RECORD
